Workbook

Sheet Assumptions
A1: RentVerified — Revenue Model Assumptions
A2: Blue cells = inputs you can change | All commissions are per-event unless marked recurring
A4: LAYER 1 — VERIFICATION (triggered every application)
A5: TransUnion commission per applicant | B5: 12 | C5: Source: TransUnion SmartMove Partner Program
A6: Tenant screening fee charged (Stripe) | B6: 45 | C6: Tenant pays RentVerified; RentVerified pays TransUnion wholesale
A7: TransUnion wholesale cost per report | B7: 30 | C7: Estimated partner rate — confirm with TransUnion
A8: Legal forms commission (NOLO/Rocket Lawyer) | B8: 20 | C8: Per landlord who purchases custom doc or legal consult
A9: Legal forms attach rate | B9: 0.15 | C9: % of landlords who buy legal docs
A11: LAYER 2 — FINTECH (triggered at lease signing)
A12: Deposit bond commission (LeaseLock/Obligo) | B12: 25 | C12: Flat fee per bond issued
A13: Rent guarantee insurance commission | B13: 175 | C13: Mid of $150–$200; ~15% of annual premium
A14: Rent guarantee attach rate | B14: 0.2 | C14: % of leases where landlord opts in
A15: Credit builder monthly (Boom) | B15: 1.5 | C15: Recurring per active tenant/month — mid of $1–$2
A16: Renters insurance monthly commission | B16: 3.5 | C16: Recurring per policy/month — mid of $2–$5
A17: Renters insurance attach rate | B17: 0.6 | C17: % of tenants who sign up for renters insurance
A19: LAYER 3 — LIFESTYLE (triggered at move-in)
A20: Internet/Cable setup commission (AT&T, Xfinity) | B20: 100 | C20: Mid of $50–$150 per new installation
A21: Internet attach rate | B21: 0.5 | C21: % of new tenants who set up through RentVerified
A22: Utility concierge commission | B22: 75 | C22: Per tenant who uses white-glove utility transfer
A23: Utility concierge attach rate | B23: 0.3 | C23: % of new tenants who use service
A24: Moving services referral fee | B24: 50 | C24: Flat fee per booked referral
A25: Moving services attach rate | B25: 0.25 | C25: % of new tenants who book movers through RentVerified
A26: Smart home hardware commission rate | B26: 0.075 | C26: 7.5% mid of 5–10% via Amazon Associates
A27: Avg smart home order value | B27: 150 | C27: Locks, cameras, etc.
A29: SUBSCRIPTION (landlord/PM monthly)
A30: Starter plan price/month | B30: 29 | C30: Up to 2 listings
A31: Pro Monthly plan price/month | B31: 79 | C31: Unlimited listings + full platform
A32: Pro Annual plan effective price/month | B32: 59 | C32: Billed $708/yr
A33: % of subscribers on Starter | B33: 0.4 | C33: Assumed mix
A34: % of subscribers on Pro Monthly | B34: 0.35 | C34: Assumed mix
A35: % of subscribers on Pro Annual | B35: 0.25 | C35: Assumed mix
A37: GROWTH ASSUMPTIONS
A38: Starting landlord subscribers (Month 1) | B38: 5 | C38: Sanders PM + early adopters
A39: Monthly new landlord subscriber growth | B39: 0.15 | C39: 15% MoM new sub growth (aggressive Utah push)
A40: Avg applications per listing per month | B40: 3 | C40: Across all active listings
A41: Avg active listings per landlord | B41: 2.5 | C41: Across starter + pro subs
A42: New tenants moved in per month (% of apps) | B42: 0.3 | C42: 30% of applicants sign a lease
A43: Avg active tenant lease months | B43: 12 | C43: Months recurring commissions flow per tenant
A45: All assumption cells are referenced by named row in the Projections sheet. Change values above to run scenarios.

Sheet Projections
A1: RentVerified — 12-Month Revenue Projections
A2: All formulas reference Assumptions sheet | Black = formula | Blue = hardcoded input
A3: Metric | B3: Mo 1 | C3: Mo 2 | D3: Mo 3 | E3: Mo 4 | F3: Mo 5 | G3: Mo 6 | H3: Mo 7 | I3: Mo 8 | J3: Mo 9 | K3: Mo 10 | L3: Mo 11 | M3: Mo 12 | N3: Full Year
A4: ── VOLUME DRIVERS
A5: Landlord subscribers | B5: =Assumptions!$B$38 -> 5 | C5: =ROUND(B5*(1+Assumptions!$B$39),0) -> 6 | D5: =ROUND(C5*(1+Assumptions!$B$39),0) -> 7 | E5: =ROUND(D5*(1+Assumptions!$B$39),0) -> 8 | F5: =ROUND(E5*(1+Assumptions!$B$39),0) -> 9 | G5: =ROUND(F5*(1+Assumptions!$B$39),0) -> 10 | H5: =ROUND(G5*(1+Assumptions!$B$39),0) -> 12 | I5: =ROUND(H5*(1+Assumptions!$B$39),0) -> 14 | J5: =ROUND(I5*(1+Assumptions!$B$39),0) -> 16 | ... M5: =ROUND(L5*(1+Assumptions!$B$39),0) -> 24 | N5: =SUM(B5:M5) -> 150
A6: Active listings | B6: =ROUND(B5*Assumptions!$B$41,0) -> 13 | C6: =ROUND(C5*Assumptions!$B$41,0) -> 15 | D6: =ROUND(D5*Assumptions!$B$41,0) -> 18 | E6: =ROUND(E5*Assumptions!$B$41,0) -> 20 | F6: =ROUND(F5*Assumptions!$B$41,0) -> 23 | G6: =ROUND(G5*Assumptions!$B$41,0) -> 25 | H6: =ROUND(H5*Assumptions!$B$41,0) -> 30 | I6: =ROUND(I5*Assumptions!$B$41,0) -> 35 | ... M6: =ROUND(M5*Assumptions!$B$41,0) -> 60 | N6: =SUM(B6:M6) -> 377
A7: Applications received | B7: =ROUND(B6*Assumptions!$B$40,0) -> 39 | C7: =ROUND(C6*Assumptions!$B$40,0) -> 45 | D7: =ROUND(D6*Assumptions!$B$40,0) -> 54 | E7: =ROUND(E6*Assumptions!$B$40,0) -> 60 | F7: =ROUND(F6*Assumptions!$B$40,0) -> 69 | G7: =ROUND(G6*Assumptions!$B$40,0) -> 75 | H7: =ROUND(H6*Assumptions!$B$40,0) -> 90 | I7: =ROUND(I6*Assumptions!$B$40,0) -> 105 | ... M7: =ROUND(M6*Assumptions!$B$40,0) -> 180 | N7: =SUM(B7:M7) -> 1131
A8: New tenants moved in | B8: =ROUND(B7*Assumptions!$B$42,0) -> 12 | C8: =ROUND(C7*Assumptions!$B$42,0) -> 14 | D8: =ROUND(D7*Assumptions!$B$42,0) -> 16 | E8: =ROUND(E7*Assumptions!$B$42,0) -> 18 | F8: =ROUND(F7*Assumptions!$B$42,0) -> 21 | G8: =ROUND(G7*Assumptions!$B$42,0) -> 23 | H8: =ROUND(H7*Assumptions!$B$42,0) -> 27 | I8: =ROUND(I7*Assumptions!$B$42,0) -> 32 | ... M8: =ROUND(M7*Assumptions!$B$42,0) -> 54 | N8: =SUM(B8:M8) -> 342
A9: Cumulative active tenants | B9: =B8 -> 12 | C9: =B9+C8 -> 26 | D9: =C9+D8 -> 42 | E9: =D9+E8 -> 60 | F9: =E9+F8 -> 81 | G9: =F9+G8 -> 104 | H9: =G9+H8 -> 131 | I9: =H9+I8 -> 163 | J9: =I9+J8 -> 199 | ... M9: =L9+M8 -> 342 | N9: =SUM(B9:M9) -> 1688
A11: LAYER 1 — VERIFICATION REVENUE
A12: TransUnion commission ($12/app) | B12: =B7*Assumptions!$B$5 -> 468 | C12: =C7*Assumptions!$B$5 -> 540 | D12: =D7*Assumptions!$B$5 -> 648 | E12: =E7*Assumptions!$B$5 -> 720 | F12: =F7*Assumptions!$B$5 -> 828 | G12: =G7*Assumptions!$B$5 -> 900 | H12: =H7*Assumptions!$B$5 -> 1080 | I12: =I7*Assumptions!$B$5 -> 1260 | ... M12: =M7*Assumptions!$B$5 -> 2160 | N12: =SUM(B12:M12) -> 13572
A13: Screening fee spread ($45 - $30 wholesale) | B13: =B7*(Assumptions!$B$6-Assumptions!$B$7) -> 585 | C13: =C7*(Assumptions!$B$6-Assumptions!$B$7) -> 675 | D13: =D7*(Assumptions!$B$6-Assumptions!$B$7) -> 810 | E13: =E7*(Assumptions!$B$6-Assumptions!$B$7) -> 900 | F13: =F7*(Assumptions!$B$6-Assumptions!$B$7) -> 1035 | G13: =G7*(Assumptions!$B$6-Assumptions!$B$7) -> 1125 | H13: =H7*(Assumptions!$B$6-Assumptions!$B$7) -> 1350 | I13: =I7*(Assumptions!$B$6-Assumptions!$B$7) -> 1575 | ... M13: =M7*(Assumptions!$B$6-Assumptions!$B$7) -> 2700 | N13: =SUM(B13:M13) -> 16965
A14: Legal forms (NOLO/Rocket Lawyer) | B14: =ROUND(B5*Assumptions!$B$9,0)*Assumptions!$B$8 -> 20 | C14: =ROUND(C5*Assumptions!$B$9,0)*Assumptions!$B$8 -> 20 | D14: =ROUND(D5*Assumptions!$B$9,0)*Assumptions!$B$8 -> 20 | E14: =ROUND(E5*Assumptions!$B$9,0)*Assumptions!$B$8 -> 20 | F14: =ROUND(F5*Assumptions!$B$9,0)*Assumptions!$B$8 -> 20 | G14: =ROUND(G5*Assumptions!$B$9,0)*Assumptions!$B$8 -> 40 | H14: =ROUND(H5*Assumptions!$B$9,0)*Assumptions!$B$8 -> 40 | I14: =ROUND(I5*Assumptions!$B$9,0)*Assumptions!$B$8 -> 40 | ... M14: =ROUND(M5*Assumptions!$B$9,0)*Assumptions!$B$8 -> 80 | N14: =SUM(B14:M14) -> 460
A15: LAYER 1 TOTAL | B15: =SUM(B12:B14) -> 1073 | C15: =SUM(C12:C14) -> 1235 | D15: =SUM(D12:D14) -> 1478 | E15: =SUM(E12:E14) -> 1640 | F15: =SUM(F12:F14) -> 1883 | G15: =SUM(G12:G14) -> 2065 | H15: =SUM(H12:H14) -> 2470 | I15: =SUM(I12:I14) -> 2875 | ... M15: =SUM(M12:M14) -> 4940 | N15: =SUM(B15:M15) -> 30997
A17: LAYER 2 — FINTECH REVENUE
A18: Deposit bonds (LeaseLock/Obligo) | B18: =B8*Assumptions!$B$12 -> 300 | C18: =C8*Assumptions!$B$12 -> 350 | D18: =D8*Assumptions!$B$12 -> 400 | E18: =E8*Assumptions!$B$12 -> 450 | F18: =F8*Assumptions!$B$12 -> 525 | G18: =G8*Assumptions!$B$12 -> 575 | H18: =H8*Assumptions!$B$12 -> 675 | I18: =I8*Assumptions!$B$12 -> 800 | ... M18: =M8*Assumptions!$B$12 -> 1350 | N18: =SUM(B18:M18) -> 8550
A19: Rent guarantee insurance | B19: =ROUND(B8*Assumptions!$B$14,0)*Assumptions!$B$13 -> 350 | C19: =ROUND(C8*Assumptions!$B$14,0)*Assumptions!$B$13 -> 525 | D19: =ROUND(D8*Assumptions!$B$14,0)*Assumptions!$B$13 -> 525 | E19: =ROUND(E8*Assumptions!$B$14,0)*Assumptions!$B$13 -> 700 | F19: =ROUND(F8*Assumptions!$B$14,0)*Assumptions!$B$13 -> 700 | G19: =ROUND(G8*Assumptions!$B$14,0)*Assumptions!$B$13 -> 875 | H19: =ROUND(H8*Assumptions!$B$14,0)*Assumptions!$B$13 -> 875 | I19: =ROUND(I8*Assumptions!$B$14,0)*Assumptions!$B$13 -> 1050 | ... M19: =ROUND(M8*Assumptions!$B$14,0)*Assumptions!$B$13 -> 1925 | N19: =SUM(B19:M19) -> 11900
A20: Credit builder recurring (Boom) | B20: =B9*Assumptions!$B$15 -> 18 | C20: =C9*Assumptions!$B$15 -> 39 | D20: =D9*Assumptions!$B$15 -> 63 | E20: =E9*Assumptions!$B$15 -> 90 | F20: =F9*Assumptions!$B$15 -> 121.5 | G20: =G9*Assumptions!$B$15 -> 156 | H20: =H9*Assumptions!$B$15 -> 196.5 | I20: =I9*Assumptions!$B$15 -> 244.5 | ... M20: =M9*Assumptions!$B$15 -> 513 | N20: =SUM(B20:M20) -> 2532
A21: Renters insurance recurring | B21: =ROUND(B9*Assumptions!$B$17,0)*Assumptions!$B$16 -> 24.5 | C21: =ROUND(C9*Assumptions!$B$17,0)*Assumptions!$B$16 -> 56 | D21: =ROUND(D9*Assumptions!$B$17,0)*Assumptions!$B$16 -> 87.5 | E21: =ROUND(E9*Assumptions!$B$17,0)*Assumptions!$B$16 -> 126 | F21: =ROUND(F9*Assumptions!$B$17,0)*Assumptions!$B$16 -> 171.5 | G21: =ROUND(G9*Assumptions!$B$17,0)*Assumptions!$B$16 -> 217 | H21: =ROUND(H9*Assumptions!$B$17,0)*Assumptions!$B$16 -> 276.5 | I21: =ROUND(I9*Assumptions!$B$17,0)*Assumptions!$B$16 -> 343 | ... M21: =ROUND(M9*Assumptions!$B$17,0)*Assumptions!$B$16 -> 717.5 | N21: =SUM(B21:M21) -> 3545.5
A22: LAYER 2 TOTAL | B22: =SUM(B18:B21) -> 692.5 | C22: =SUM(C18:C21) -> 970 | D22: =SUM(D18:D21) -> 1075.5 | E22: =SUM(E18:E21) -> 1366 | F22: =SUM(F18:F21) -> 1518 | G22: =SUM(G18:G21) -> 1823 | H22: =SUM(H18:H21) -> 2023 | I22: =SUM(I18:I21) -> 2437.5 | ... M22: =SUM(M18:M21) -> 4505.5 | N22: =SUM(B22:M22) -> 26527.5
A24: LAYER 3 — LIFESTYLE REVENUE
A25: Internet/Cable setup | B25: =ROUND(B8*Assumptions!$B$21,0)*Assumptions!$B$20 -> 600 | C25: =ROUND(C8*Assumptions!$B$21,0)*Assumptions!$B$20 -> 700 | D25: =ROUND(D8*Assumptions!$B$21,0)*Assumptions!$B$20 -> 800 | E25: =ROUND(E8*Assumptions!$B$21,0)*Assumptions!$B$20 -> 900 | F25: =ROUND(F8*Assumptions!$B$21,0)*Assumptions!$B$20 -> 1100 | G25: =ROUND(G8*Assumptions!$B$21,0)*Assumptions!$B$20 -> 1200 | H25: =ROUND(H8*Assumptions!$B$21,0)*Assumptions!$B$20 -> 1400 | I25: =ROUND(I8*Assumptions!$B$21,0)*Assumptions!$B$20 -> 1600 | ... M25: =ROUND(M8*Assumptions!$B$21,0)*Assumptions!$B$20 -> 2700 | N25: =SUM(B25:M25) -> 17300
A26: Utility concierge | B26: =ROUND(B8*Assumptions!$B$23,0)*Assumptions!$B$22 -> 300 | C26: =ROUND(C8*Assumptions!$B$23,0)*Assumptions!$B$22 -> 300 | D26: =ROUND(D8*Assumptions!$B$23,0)*Assumptions!$B$22 -> 375 | E26: =ROUND(E8*Assumptions!$B$23,0)*Assumptions!$B$22 -> 375 | F26: =ROUND(F8*Assumptions!$B$23,0)*Assumptions!$B$22 -> 450 | G26: =ROUND(G8*Assumptions!$B$23,0)*Assumptions!$B$22 -> 525 | H26: =ROUND(H8*Assumptions!$B$23,0)*Assumptions!$B$22 -> 600 | I26: =ROUND(I8*Assumptions!$B$23,0)*Assumptions!$B$22 -> 750 | ... M26: =ROUND(M8*Assumptions!$B$23,0)*Assumptions!$B$22 -> 1200 | N26: =SUM(B26:M26) -> 7650
A27: Moving services | B27: =ROUND(B8*Assumptions!$B$25,0)*Assumptions!$B$24 -> 150 | C27: =ROUND(C8*Assumptions!$B$25,0)*Assumptions!$B$24 -> 200 | D27: =ROUND(D8*Assumptions!$B$25,0)*Assumptions!$B$24 -> 200 | E27: =ROUND(E8*Assumptions!$B$25,0)*Assumptions!$B$24 -> 250 | F27: =ROUND(F8*Assumptions!$B$25,0)*Assumptions!$B$24 -> 250 | G27: =ROUND(G8*Assumptions!$B$25,0)*Assumptions!$B$24 -> 300 | H27: =ROUND(H8*Assumptions!$B$25,0)*Assumptions!$B$24 -> 350 | I27: =ROUND(I8*Assumptions!$B$25,0)*Assumptions!$B$24 -> 400 | ... M27: =ROUND(M8*Assumptions!$B$25,0)*Assumptions!$B$24 -> 700 | N27: =SUM(B27:M27) -> 4350
A28: Smart home hardware | B28: =ROUND(B8*Assumptions!$B$27*Assumptions!$B$26,0) -> 135 | C28: =ROUND(C8*Assumptions!$B$27*Assumptions!$B$26,0) -> 158 | D28: =ROUND(D8*Assumptions!$B$27*Assumptions!$B$26,0) -> 180 | E28: =ROUND(E8*Assumptions!$B$27*Assumptions!$B$26,0) -> 203 | F28: =ROUND(F8*Assumptions!$B$27*Assumptions!$B$26,0) -> 236 | G28: =ROUND(G8*Assumptions!$B$27*Assumptions!$B$26,0) -> 259 | H28: =ROUND(H8*Assumptions!$B$27*Assumptions!$B$26,0) -> 304 | I28: =ROUND(I8*Assumptions!$B$27*Assumptions!$B$26,0) -> 360 | ... M28: =ROUND(M8*Assumptions!$B$27*Assumptions!$B$26,0) -> 608 | N28: =SUM(B28:M28) -> 3849
A29: LAYER 3 TOTAL | B29: =SUM(B25:B28) -> 1185 | C29: =SUM(C25:C28) -> 1358 | D29: =SUM(D25:D28) -> 1555 | E29: =SUM(E25:E28) -> 1728 | F29: =SUM(F25:F28) -> 2036 | G29: =SUM(G25:G28) -> 2284 | H29: =SUM(H25:H28) -> 2654 | I29: =SUM(I25:I28) -> 3110 | ... M29: =SUM(M25:M28) -> 5208 | N29: =SUM(B29:M29) -> 33149
A31: SUBSCRIPTION REVENUE
A32: Starter subscribers | B32: =ROUND(B5*Assumptions!$B$33,0) -> 2 | C32: =ROUND(C5*Assumptions!$B$33,0) -> 2 | D32: =ROUND(D5*Assumptions!$B$33,0) -> 3 | E32: =ROUND(E5*Assumptions!$B$33,0) -> 3 | F32: =ROUND(F5*Assumptions!$B$33,0) -> 4 | G32: =ROUND(G5*Assumptions!$B$33,0) -> 4 | H32: =ROUND(H5*Assumptions!$B$33,0) -> 5 | I32: =ROUND(I5*Assumptions!$B$33,0) -> 6 | ... M32: =ROUND(M5*Assumptions!$B$33,0) -> 10 | N32: =SUM(B32:M32) -> 60
A33: Pro Monthly subscribers | B33: =ROUND(B5*Assumptions!$B$34,0) -> 2 | C33: =ROUND(C5*Assumptions!$B$34,0) -> 2 | D33: =ROUND(D5*Assumptions!$B$34,0) -> 2 | E33: =ROUND(E5*Assumptions!$B$34,0) -> 3 | F33: =ROUND(F5*Assumptions!$B$34,0) -> 3 | G33: =ROUND(G5*Assumptions!$B$34,0) -> 4 | H33: =ROUND(H5*Assumptions!$B$34,0) -> 4 | I33: =ROUND(I5*Assumptions!$B$34,0) -> 5 | ... M33: =ROUND(M5*Assumptions!$B$34,0) -> 8 | N33: =SUM(B33:M33) -> 52
A34: Pro Annual subscribers | B34: =ROUND(B5*Assumptions!$B$35,0) -> 1 | C34: =ROUND(C5*Assumptions!$B$35,0) -> 2 | D34: =ROUND(D5*Assumptions!$B$35,0) -> 2 | E34: =ROUND(E5*Assumptions!$B$35,0) -> 2 | F34: =ROUND(F5*Assumptions!$B$35,0) -> 2 | G34: =ROUND(G5*Assumptions!$B$35,0) -> 3 | H34: =ROUND(H5*Assumptions!$B$35,0) -> 3 | I34: =ROUND(I5*Assumptions!$B$35,0) -> 4 | ... M34: =ROUND(M5*Assumptions!$B$35,0) -> 6 | N34: =SUM(B34:M34) -> 39
A35: Subscription revenue | B35: =B32*Assumptions!$B$30+B33*Assumptions!$B$31+B34*Assumptions!$B$32 -> 275 | C35: =C32*Assumptions!$B$30+C33*Assumptions!$B$31+C34*Assumptions!$B$32 -> 334 | D35: =D32*Assumptions!$B$30+D33*Assumptions!$B$31+D34*Assumptions!$B$32 -> 363 | E35: =E32*Assumptions!$B$30+E33*Assumptions!$B$31+E34*Assumptions!$B$32 -> 442 | F35: =F32*Assumptions!$B$30+F33*Assumptions!$B$31+F34*Assumptions!$B$32 -> 471 | G35: =G32*Assumptions!$B$30+G33*Assumptions!$B$31+G34*Assumptions!$B$32 -> 609 | H35: =H32*Assumptions!$B$30+H33*Assumptions!$B$31+H34*Assumptions!$B$32 -> 638 | I35: =I32*Assumptions!$B$30+I33*Assumptions!$B$31+I34*Assumptions!$B$32 -> 805 | ... M35: =M32*Assumptions!$B$30+M33*Assumptions!$B$31+M34*Assumptions!$B$32 -> 1276 | N35: =SUM(B35:M35) -> 8149
A36: SUBSCRIPTION TOTAL | B36: =B35 -> 275 | C36: =C35 -> 334 | D36: =D35 -> 363 | E36: =E35 -> 442 | F36: =F35 -> 471 | G36: =G35 -> 609 | H36: =H35 -> 638 | I36: =I35 -> 805 | ... M36: =M35 -> 1276 | N36: =SUM(B36:M36) -> 8149
A39: ▶ TOTAL MONTHLY REVENUE | B39: =B15+B22+B29+B36 -> 3225.5 | C39: =C15+C22+C29+C36 -> 3897 | D39: =D15+D22+D29+D36 -> 4471.5 | E39: =E15+E22+E29+E36 -> 5176 | F39: =F15+F22+F29+F36 -> 5908 | G39: =G15+G22+G29+G36 -> 6781 | H39: =H15+H22+H29+H36 -> 7785 | I39: =I15+I22+I29+I36 -> 9227.5 | ... M39: =M15+M22+M29+M36 -> 15929.5 | N39: =SUM(B39:M39) -> 98822.5
A40: MoM Revenue Growth | B40: — | C40: =IFERROR((C39-B39)/B39,"-") -> 0.20818478 | D40: =IFERROR((D39-C39)/C39,"-") -> 0.14742109 | E40: =IFERROR((E39-D39)/D39,"-") -> 0.15755339 | F40: =IFERROR((F39-E39)/E39,"-") -> 0.14142195 | G40: =IFERROR((G39-F39)/F39,"-") -> 0.14776574 | H40: =IFERROR((H39-G39)/G39,"-") -> 0.14806076 | I40: =IFERROR((I39-H39)/H39,"-") -> 0.18529223 | J40: =IFERROR((J39-I39)/I39,"-") -> 0.13616906 | ... M40: =IFERROR((M39-L39)/L39,"-") -> 0.1369687 | N40: —

Sheet Summary
A1: RentVerified — Full Year Revenue Mix
A3: Revenue Stream | B3: Full Year ($) | C3: % of Total | D3: Affiliate / Partner
A4: TransUnion commission | B4: =Projections!N12 -> 13572 | C4: =IFERROR(B4/B16,0) -> 0.13733714 | D4: TransUnion SmartMove
A5: Screening fee spread | B5: =Projections!N13 -> 16965 | C5: =IFERROR(B5/B16,0) -> 0.17167143 | D5: TransUnion SmartMove
A6: Legal forms | B6: =Projections!N14 -> 460 | C6: =IFERROR(B6/B16,0) -> 0.0046548104 | D6: NOLO / Rocket Lawyer
A7: Deposit bonds | B7: =Projections!N18 -> 8550 | C7: =IFERROR(B7/B16,0) -> 0.086518758 | D7: LeaseLock / Obligo
A8: Rent guarantee insurance | B8: =Projections!N19 -> 11900 | C8: =IFERROR(B8/B16,0) -> 0.12041792 | D8: Partner insurer
A9: Credit builder (recurring) | B9: =Projections!N20 -> 2532 | C9: =IFERROR(B9/B16,0) -> 0.025621695 | D9: Boom
A10: Renters insurance (recurring) | B10: =Projections!N21 -> 3545.5 | C10: =IFERROR(B10/B16,0) -> 0.035877457 | D10: Lemonade / partner
A11: Internet/Cable setup | B11: =Projections!N25 -> 17300 | C11: =IFERROR(B11/B16,0) -> 0.17506135 | D11: AT&T, Xfinity
A12: Utility concierge | B12: =Projections!N26 -> 7650 | C12: =IFERROR(B12/B16,0) -> 0.077411521 | D12: Utility concierge partner
A13: Moving services | B13: =Projections!N27 -> 4350 | C13: =IFERROR(B13/B16,0) -> 0.044018316 | D13: Moving co. referral
A14: Smart home hardware | B14: =Projections!N28 -> 3849 | C14: =IFERROR(B14/B16,0) -> 0.03894862 | D14: Amazon Associates
A15: Subscription revenue | B15: =Projections!N35 -> 8149 | C15: =IFERROR(B15/B16,0) -> 0.082460978 | D15: Direct (Stripe)
A16: TOTAL ANNUAL REVENUE | B16: =SUM(B4:B15) -> 98822.5 | C16: 100.0%
A18: Note: Recurring revenue streams (credit builder, renters insurance) grow each month as cumulative active tenants increase. Projections assume 15% MoM landlord subscriber growth starting from 5 subscribers.
